dtale/__init__.py
dtale/app.py
dtale/auth.py
dtale/code_export.py
dtale/column_analysis.py
dtale/column_builders.py
dtale/column_filters.py
dtale/column_replacements.py
dtale/combine_data.py
dtale/config.py
dtale/constants.py
dtale/correlations.py
dtale/data_reshapers.py
dtale/datasets.py
dtale/describe.py
dtale/duplicate_checks.py
dtale/env_util.py
dtale/gage_rnr.py
dtale/global_state.py
dtale/pandas_util.py
dtale/predefined_filters.py
dtale/query.py
dtale/timeseries_analysis.py
dtale/utils.py
dtale/views.py
dtale/charts/__init__.py
dtale/charts/utils.py
dtale/cli/__init__.py
dtale/cli/clickutils.py
dtale/cli/script.py
dtale/cli/streamlit_script.py
dtale/cli/loaders/__init__.py
dtale/cli/loaders/arctic_loader.py
dtale/cli/loaders/arcticdb_loader.py
dtale/cli/loaders/csv_loader.py
dtale/cli/loaders/excel_loader.py
dtale/cli/loaders/json_loader.py
dtale/cli/loaders/parquet_loader.py
dtale/cli/loaders/r_loader.py
dtale/cli/loaders/sqlite_loader.py
dtale/dash_application/__init__.py
dtale/dash_application/charts.py
dtale/dash_application/custom_geojson.py
dtale/dash_application/drilldown_modal.py
dtale/dash_application/exceptions.py
dtale/dash_application/extended_aggregations.py
dtale/dash_application/lock_zoom.py
dtale/dash_application/saved_charts.py
dtale/dash_application/topojson_injections.py
dtale/dash_application/utils.py
dtale/dash_application/views.py
dtale/dash_application/components/DashColorscales.py
dtale/dash_application/components/Wordcloud.py
dtale/dash_application/components/__init__.py
dtale/dash_application/components/_imports_.py
dtale/dash_application/components/metadata.json
dtale/dash_application/components/package-info.json
dtale/dash_application/layout/__init__.py
dtale/dash_application/layout/layout.py
dtale/dash_application/layout/utils.py
dtale/django/__init__.py
dtale/django/dispatcher.py
dtale/ppscore/__init__.py
dtale/ppscore/calculation.py
dtale/static/css/dash.css
dtale/static/css/github_fork.css
dtale/static/css/main.css
dtale-3.18.1.dist-info/licenses/LICENSE
dtale-3.18.1.dist-info/METADATA
dtale-3.18.1.dist-info/WHEEL
dtale-3.18.1.dist-info/entry_points.txt
dtale-3.18.1.dist-info/top_level.txt
dtale-3.18.1.dist-info/RECORD
