Metadata-Version: 2.4
Name: dtale
Version: 3.18.1
Summary: Web Client for Visualizing Pandas Objects
Home-page: https://github.com/man-group/dtale
Author: MAN Alpha Technology
Author-email: ManAlphaTech@man.com
License: LGPL
Keywords: numeric,pandas,visualization,flask
Classifier: Development Status :: 4 - Beta
Classifier: License :: OSI Approved :: GNU Library or Lesser General Public License (LGPL)
Classifier: Operating System :: OS Independent
Classifier: Intended Audience :: Science/Research
Classifier: Programming Language :: Python
Classifier: Topic :: Scientific/Engineering
Classifier: Programming Language :: Python :: 2.7
Classifier: Programming Language :: Python :: 3.6
Classifier: Programming Language :: Python :: 3.7
Classifier: Programming Language :: Python :: 3.8
Classifier: Programming Language :: Python :: 3.9
Classifier: Programming Language :: Python :: 3.10
Classifier: Programming Language :: Python :: 3.11
License-File: LICENSE
Requires-Dist: lz4<=2.2.1; python_version == "2.7"
Requires-Dist: lz4<=3.1.10; python_version == "3.6"
Requires-Dist: lz4; python_version > "3.6"
Requires-Dist: beautifulsoup4!=4.13.0b2; python_version > "3.0"
Requires-Dist: beautifulsoup4<=4.9.3; python_version == "2.7"
Requires-Dist: Brotli<=1.0.9; python_version == "2.7"
Requires-Dist: certifi<=2021.10.8; python_version == "2.7"
Requires-Dist: certifi; python_version > "3.0"
Requires-Dist: cycler; python_version > "3.6"
Requires-Dist: cycler<=0.11.0; python_version == "3.6"
Requires-Dist: cycler<=0.10.0; python_version == "2.7"
Requires-Dist: dash<=1.21.0; python_version == "2.7"
Requires-Dist: dash<=2.0.0; python_version == "3.6"
Requires-Dist: dash!=2.13.0; python_version == "3.7"
Requires-Dist: dash<=2.18.2; python_version > "3.7"
Requires-Dist: dash-bootstrap-components==0.13.1; python_version == "2.7"
Requires-Dist: dash-bootstrap-components<=1.7.1; python_version > "3.0"
Requires-Dist: dash_daq<=0.5.0
Requires-Dist: dataclasses<1; python_version == "3.6"
Requires-Dist: decorator<=4.4.2; python_version == "2.7"
Requires-Dist: et_xmlfile<=1.0.1; python_version < "3.6"
Requires-Dist: et_xmlfile; python_version >= "3.6"
Requires-Dist: Flask<=1.1.4; python_version < "3.7"
Requires-Dist: Flask<2.3; python_version == "3.7"
Requires-Dist: Flask; python_version >= "3.8"
Requires-Dist: Flask-Compress<=1.15; python_version <= "3.8"
Requires-Dist: Flask-Compress; python_version > "3.8"
Requires-Dist: future>=0.14.0
Requires-Dist: immutables<=0.19; python_version == "3.6"
Requires-Dist: itsdangerous<=1.1.0; python_version < "3.7"
Requires-Dist: itsdangerous<=2.1.2; python_version == "3.7"
Requires-Dist: itsdangerous; python_version >= "3.8"
Requires-Dist: joblib<=1.1.1; python_version == "3.6"
Requires-Dist: joblib<=1.3.2; python_version == "3.7"
Requires-Dist: kaleido<=0.2.1; python_version <= "3.8"
Requires-Dist: kaleido; python_version >= "3.9"
Requires-Dist: kiwisolver<=1.1.0; python_version < "3.6"
Requires-Dist: kiwisolver<=1.2.0; python_version == "3.6"
Requires-Dist: kiwisolver<=1.4.5; python_version == "3.7"
Requires-Dist: MarkupSafe<=1.1.1; python_version == "2.7"
Requires-Dist: MarkupSafe<=2.0.1; python_version == "3.6"
Requires-Dist: MarkupSafe<=2.1.5; python_version == "3.7"
Requires-Dist: MarkupSafe<=2.1.5; python_version == "3.8"
Requires-Dist: matplotlib<=2.2.5; python_version == "2.7"
Requires-Dist: matplotlib<=3.3.4; python_version == "3.6"
Requires-Dist: matplotlib<=3.5.3; python_version == "3.7"
Requires-Dist: matplotlib<=3.7.2; python_version == "3.8"
Requires-Dist: matplotlib; python_version >= "3.9"
Requires-Dist: missingno
Requires-Dist: networkx<=2.2; python_version <= "3.4"
Requires-Dist: networkx<=2.4; python_version == "3.5"
Requires-Dist: networkx<=2.5.1; python_version == "3.6"
Requires-Dist: networkx<=2.6.3; python_version == "3.7"
Requires-Dist: networkx<=3.1; python_version == "3.8"
Requires-Dist: networkx<=3.2.1; python_version == "3.9"
Requires-Dist: networkx; python_version > "3.9"
Requires-Dist: numpy<=1.16.6; python_version < "3.0"
Requires-Dist: numpy; python_version >= "3.0"
Requires-Dist: openpyxl<=2.6.4; python_version < "3.0"
Requires-Dist: openpyxl!=3.2.0b1; python_version >= "3.0"
Requires-Dist: packaging
Requires-Dist: pandas
Requires-Dist: pkginfo
Requires-Dist: plotly<=4.14.3; python_version < "3.6"
Requires-Dist: plotly; python_version >= "3.6"
Requires-Dist: pyparsing<=2.4.7; python_version == "2.7"
Requires-Dist: requests; python_version >= "3.8"
Requires-Dist: requests<=2.31.0; python_version == "3.7"
Requires-Dist: requests<=2.27.1; python_version <= "3.6"
Requires-Dist: scikit-learn<=0.20.4; python_version < "3.0"
Requires-Dist: scikit-learn<=0.24.2; python_version == "3.6"
Requires-Dist: scikit-learn<=1.0.2; python_version == "3.7"
Requires-Dist: scikit-learn<=1.3.2; python_version == "3.8"
Requires-Dist: scikit-learn; python_version > "3.8"
Requires-Dist: scipy<=1.2.3; python_version == "2.7"
Requires-Dist: scipy<=1.5.4; python_version == "3.0"
Requires-Dist: scipy<=1.5.4; python_version == "3.1"
Requires-Dist: scipy<=1.5.4; python_version == "3.2"
Requires-Dist: scipy<=1.5.4; python_version == "3.3"
Requires-Dist: scipy<=1.5.4; python_version == "3.4"
Requires-Dist: scipy<=1.5.4; python_version == "3.5"
Requires-Dist: scipy<=1.5.4; python_version == "3.6"
Requires-Dist: scipy<=1.7.3; python_version == "3.7"
Requires-Dist: scipy<=1.10.1; python_version == "3.8"
Requires-Dist: scipy<=1.13.1; python_version == "3.9"
Requires-Dist: scipy!=1.12.0rc1,!=1.14.0,!=1.14.0rc1,!=1.14.0rc2,<1.16.0; python_version >= "3.10"
Requires-Dist: seaborn<=0.9.1; python_version < "3.6"
Requires-Dist: seaborn<=0.11.2; python_version == "3.6"
Requires-Dist: seaborn<=0.12.2; python_version == "3.7"
Requires-Dist: seaborn; python_version > "3.7"
Requires-Dist: squarify
Requires-Dist: statsmodels<=0.10.2; python_version == "2.7"
Requires-Dist: statsmodels<=0.12.2; python_version == "3.0"
Requires-Dist: statsmodels<=0.12.2; python_version == "3.1"
Requires-Dist: statsmodels<=0.12.2; python_version == "3.2"
Requires-Dist: statsmodels<=0.12.2; python_version == "3.3"
Requires-Dist: statsmodels<=0.12.2; python_version == "3.4"
Requires-Dist: statsmodels<=0.12.2; python_version == "3.5"
Requires-Dist: statsmodels<=0.12.2; python_version == "3.6"
Requires-Dist: statsmodels<=0.12.2; python_version == "3.7"
Requires-Dist: statsmodels<=0.14.1; python_version == "3.8"
Requires-Dist: statsmodels; python_version > "3.8"
Requires-Dist: strsimpy
Requires-Dist: six
Requires-Dist: tenacity<=7.0.0; python_version == "3.6"
Requires-Dist: threadpoolctl<=3.1.0; python_version == "3.6"
Requires-Dist: threadpoolctl<=3.1.0; python_version == "3.7"
Requires-Dist: urllib3<=2.0.7; python_version == "3.7"
Requires-Dist: werkzeug<=1.0.1; python_version <= "3.6"
Requires-Dist: werkzeug==2.2.3; python_version == "3.7"
Requires-Dist: werkzeug; python_version > "3.7"
Requires-Dist: xarray<=0.11.3; python_version < "3.0"
Requires-Dist: xarray; python_version >= "3.0"
Requires-Dist: xlrd
Requires-Dist: zipp<=3.15.0; python_version == "3.6"
Requires-Dist: zstandard<=0.20.0; python_version == "3.6"
Requires-Dist: zstandard<=0.21.0; python_version == "3.7"
Requires-Dist: zstandard<=0.14.0; python_version == "2.7"
Provides-Extra: arctic
Requires-Dist: arctic<=1.79.4; extra == "arctic"
Provides-Extra: arcticdb
Requires-Dist: arcticdb; extra == "arcticdb"
Provides-Extra: dash-bio
Requires-Dist: ParmEd==3.4.3; python_version == "3.6" and extra == "dash-bio"
Requires-Dist: dash-bio; python_version > "3.0" and extra == "dash-bio"
Requires-Dist: dash-bio==0.7.1; python_version == "2.7" and extra == "dash-bio"
Provides-Extra: ngrok
Requires-Dist: flask-ngrok; python_version > "3.0" and extra == "ngrok"
Provides-Extra: r
Requires-Dist: rpy2; python_version > "3.0" and extra == "r"
Provides-Extra: redis
Requires-Dist: redis; extra == "redis"
Requires-Dist: redislite; extra == "redis"
Provides-Extra: streamlit
Requires-Dist: streamlit; extra == "streamlit"
Provides-Extra: swifter
Requires-Dist: swifter; extra == "swifter"
Provides-Extra: tests
Requires-Dist: importlib-metadata<=3.7.3; python_version <= "3.6" and extra == "tests"
Requires-Dist: importlib-metadata; python_version != "3.6" and extra == "tests"
Requires-Dist: ipython<8.0.0; extra == "tests"
Requires-Dist: mock; extra == "tests"
Requires-Dist: nbconvert; extra == "tests"
Requires-Dist: pytest; extra == "tests"
Requires-Dist: pytest-cov; extra == "tests"
Requires-Dist: pytest-server-fixtures<=1.7.0; python_version == "2.7" and extra == "tests"
Requires-Dist: pytest-server-fixtures; python_version >= "3.6" and extra == "tests"
Dynamic: author
Dynamic: author-email
Dynamic: classifier
Dynamic: description
Dynamic: home-page
Dynamic: keywords
Dynamic: license
Dynamic: license-file
Dynamic: provides-extra
Dynamic: requires-dist
Dynamic: summary
